AEFG
