Metadata-Version: 2.1
Name: AEFG
Version: 1.0.1
Summary: AEFG is an atomic environment-based functional group fragmentation method.
Author: dehang wang
Author-email: 
Keywords: python,menu,dumb_menu,windows,mac,linux
Classifier: Development Status :: 1 - Planning
Classifier: Intended Audience :: Developers
Classifier: Programming Language :: Python :: 3
Classifier: Operating System :: Unix
Classifier: Operating System :: MacOS :: MacOS X
Classifier: Operating System :: Microsoft :: Windows
